[
  {
    "type": {
      "key": "weeding",
      "name": "الزفاف",
      "badgeColor": "gold"
    },
    "title": "الباكج الثالث",
    "price": 70000.0,
    "currency": "ريال",
    "badge": null,
    "is_discount": false,
    "discount_percent": 0,
    "is_vip": false,
    "is_popular": false,
    "details": {
      "time": "مدة خمس ساعات (تحديد الوقت على حسب الطلب)",
      "location": "اب"
    },
    "featuresGrid": {
      "items": [
        {
          "title": "التصوير",
          "features": [
            "لا محدود"
          ]
        },
        {
          "title": "الفيديوهات",
          "features": [
            "تصوير فيديو زفة العروسه",
            "تصوير فيديو زفة العروسين",
            "تقطيع الجاتو"
          ]
        },
        {
          "title": "المميزات",
          "features": [
            "تعديل الصور",
            "طباعة 20 صوره مقاس A5",
            "تسليم الصور والفيدوهات داخل فلاش ميموري"
          ]
        }
      ]
    },
    "booking": {
      "title": null,
      "items": []
    },
    "notes": {
      "title": null,
      "items": []
    },
    "footer": {
      "text": null,
      "social": {}
    },
    "logoIcon": "fa fa-camera"
  },
  {
    "type": {
      "key": "weeding",
      "name": "الزفاف",
      "badgeColor": "gold"
    },
    "title": "الباكج الثاني",
    "price": 45000.0,
    "currency": "ريال",
    "badge": "يوجد عرض",
    "is_discount": false,
    "discount_percent": 0,
    "is_vip": false,
    "is_popular": false,
    "details": {
      "time": "مدة ساعتين(تحديد الوقت على حسب الطلب)",
      "location": "اب"
    },
    "featuresGrid": {
      "items": [
        {
          "title": "الصور",
          "features": [
            "لا محدود"
          ]
        },
        {
          "title": "الفيديو",
          "features": [
            "فيديو زفة واحد"
          ]
        },
        {
          "title": "المميزات",
          "features": []
        }
      ]
    },
    "booking": {
      "title": null,
      "items": []
    },
    "notes": {
      "title": null,
      "items": []
    },
    "footer": {
      "text": null,
      "social": {}
    },
    "logoIcon": "fa fa-home"
  },
  {
    "type": {
      "key": "weeding",
      "name": "الزفاف",
      "badgeColor": "gold"
    },
    "title": "الباكج الاول",
    "price": 30000.0,
    "currency": "ريال",
    "badge": null,
    "is_discount": false,
    "discount_percent": 0,
    "is_vip": false,
    "is_popular": false,
    "details": {
      "time": "لمدة ساعة",
      "location": "إب"
    },
    "featuresGrid": {
      "items": [
        {
          "title": "المميزات",
          "features": [
            "تصوير صور فقط",
            "تسليم الصور بنفس اليوم داخل فلاش ميموري"
          ]
        }
      ]
    },
    "booking": {
      "title": null,
      "items": []
    },
    "notes": {
      "title": null,
      "items": []
    },
    "footer": {
      "text": null,
      "social": {}
    },
    "logoIcon": "fa fa-camera"
  },
  {
    "type": {
      "key": "weeding",
      "name": "الزفاف",
      "badgeColor": "gold"
    },
    "title": "الباكج الرابع",
    "price": 120000.0,
    "currency": "ريال",
    "badge": null,
    "is_discount": false,
    "discount_percent": 0,
    "is_vip": false,
    "is_popular": false,
    "details": {
      "time": "من الساعة 1 الى 8",
      "location": "اب"
    },
    "featuresGrid": {
      "items": [
        {
          "title": "التصوير",
          "features": [
            "لا محدود للعرس كامل"
          ]
        },
        {
          "title": "الفيديو",
          "features": [
            "تصوير فيديو زفة العروسة",
            "زفة العريسين",
            "دخول الاهل",
            "تقطيع الجاتو"
          ]
        },
        {
          "title": "المميزات",
          "features": [
            "تصوير فيديو برونين (مانع الاهتزاز)",
            "كليب ممنتج لتفاصيل العرس والعريسين",
            "تعديل صور",
            "طباعة 30 صوره مقاس A5",
            "تسليم الصور والفيدوهات داخل فلاش ميموري"
          ]
        }
      ]
    },
    "booking": {
      "title": null,
      "items": []
    },
    "notes": {
      "title": null,
      "items": []
    },
    "footer": {
      "text": null,
      "social": {}
    },
    "logoIcon": null
  },
  {
    "type": {
      "key": "birthdays_graduations",
      "name": "التخرج واعياد الميلاد",
      "badgeColor": "red"
    },
    "title": "الباكج الاول",
    "price": 15000.0,
    "currency": "ريال",
    "badge": null,
    "is_discount": false,
    "discount_percent": 0,
    "is_vip": false,
    "is_popular": false,
    "details": {
      "time": "ساعه واحده",
      "location": "اب"
    },
    "featuresGrid": {
      "items": [
        {
          "title": "الصور",
          "features": [
            "تصوير لا محدود"
          ]
        },
        {
          "title": "المميزات",
          "features": [
            "تسليم الصور بنفس اليوم"
          ]
        }
      ]
    },
    "booking": {
      "title": null,
      "items": []
    },
    "notes": {
      "title": null,
      "items": []
    },
    "footer": {
      "text": null,
      "social": {}
    },
    "logoIcon": null
  },
  {
    "type": {
      "key": "birthdays_graduations",
      "name": "التخرج واعياد الميلاد",
      "badgeColor": "red"
    },
    "title": "الباكج الثاني",
    "price": 25000.0,
    "currency": "ريال",
    "badge": null,
    "is_discount": false,
    "discount_percent": 0,
    "is_vip": false,
    "is_popular": false,
    "details": {
      "time": "ساعتين",
      "location": "اب"
    },
    "featuresGrid": {
      "items": [
        {
          "title": "الصور",
          "features": [
            "لا محدود"
          ]
        },
        {
          "title": "الفيديوهات",
          "features": [
            "فيديو مونتاج قصير"
          ]
        },
        {
          "title": "المميزات",
          "features": [
            "تعديل صور",
            "التسليم داخل فلاش ميموري"
          ]
        }
      ]
    },
    "booking": {
      "title": null,
      "items": []
    },
    "notes": {
      "title": null,
      "items": []
    },
    "footer": {
      "text": null,
      "social": {}
    },
    "logoIcon": null
  },
  {
    "type": {
      "key": "birthdays_graduations",
      "name": "التخرج واعياد الميلاد",
      "badgeColor": "red"
    },
    "title": "الباكج الثالث",
    "price": 30000.0,
    "currency": "ريال",
    "badge": null,
    "is_discount": false,
    "discount_percent": 0,
    "is_vip": false,
    "is_popular": false,
    "details": {
      "time": "ساعتين",
      "location": "اب"
    },
    "featuresGrid": {
      "items": [
        {
          "title": "الصور",
          "features": [
            "تصوير لا محدود"
          ]
        },
        {
          "title": "الفيديوهات",
          "features": [
            "فيديو مونتاج قصير"
          ]
        },
        {
          "title": "المميزات",
          "features": [
            "تعديل صور",
            "طباعة 15 صوره مقاس A5",
            "تسليم الصور داخل فلاش ميموري"
          ]
        }
      ]
    },
    "booking": {
      "title": null,
      "items": []
    },
    "notes": {
      "title": null,
      "items": []
    },
    "footer": {
      "text": null,
      "social": {}
    },
    "logoIcon": null
  }
]